{
  "city": "Lilongwe",
  "country": "Malawi",
  "data": [
    {
      "year": 1850,
      "value": 13.70223898
    },
    {
      "year": 1851,
      "value": 11.83637958
    },
    {
      "year": 1852,
      "value": 12.00412173
    },
    {
      "year": 1853,
      "value": 12.49727675
    },
    {
      "year": 1854,
      "value": 12.91390482
    },
    {
      "year": 1855,
      "value": 12.96814663
    },
    {
      "year": 1856,
      "value": 11.8189759
    },
    {
      "year": 1857,
      "value": 12.82826051
    },
    {
      "year": 1858,
      "value": 14.48974701
    },
    {
      "year": 1859,
      "value": 11.78496685
    },
    {
      "year": 1860,
      "value": 11.80395442
    },
    {
      "year": 1861,
      "value": 12.81845101
    },
    {
      "year": 1862,
      "value": 11.97664664
    },
    {
      "year": 1863,
      "value": 11.95703708
    },
    {
      "year": 1864,
      "value": 13.13030174
    },
    {
      "year": 1865,
      "value": 12.74789784
    },
    {
      "year": 1866,
      "value": 12.41536825
    },
    {
      "year": 1867,
      "value": 13.09220381
    },
    {
      "year": 1868,
      "value": 13.68454502
    },
    {
      "year": 1869,
      "value": 13.66629128
    },
    {
      "year": 1870,
      "value": 12.63027042
    },
    {
      "year": 1871,
      "value": 12.76242765
    },
    {
      "year": 1872,
      "value": 11.77004369
    },
    {
      "year": 1873,
      "value": 12.97594568
    },
    {
      "year": 1874,
      "value": 13.42877479
    },
    {
      "year": 1875,
      "value": 13.10300334
    },
    {
      "year": 1876,
      "value": 12.17814163
    },
    {
      "year": 1877,
      "value": 13.08758717
    },
    {
      "year": 1878,
      "value": 14.44993845
    },
    {
      "year": 1879,
      "value": 12.40067767
    },
    {
      "year": 1880,
      "value": 12.38690904
    },
    {
      "year": 1881,
      "value": 12.14162873
    },
    {
      "year": 1882,
      "value": 12.64237475
    },
    {
      "year": 1883,
      "value": 12.75757473
    },
    {
      "year": 1884,
      "value": 13.38570058
    },
    {
      "year": 1885,
      "value": 12.63360972
    },
    {
      "year": 1886,
      "value": 12.9492044
    },
    {
      "year": 1887,
      "value": 13.24322586
    },
    {
      "year": 1888,
      "value": 13.01678103
    },
    {
      "year": 1889,
      "value": 13.1270983
    },
    {
      "year": 1890,
      "value": 13.10909476
    },
    {
      "year": 1891,
      "value": 12.84755942
    },
    {
      "year": 1892,
      "value": 13.02772649
    },
    {
      "year": 1893,
      "value": 12.89959829
    },
    {
      "year": 1894,
      "value": 14.36643343
    },
    {
      "year": 1895,
      "value": 13.74274175
    },
    {
      "year": 1896,
      "value": 11.99725096
    },
    {
      "year": 1897,
      "value": 13.7753972
    },
    {
      "year": 1898,
      "value": 14.25921684
    },
    {
      "year": 1899,
      "value": 13.08209285
    },
    {
      "year": 1900,
      "value": 13.69243838
    },
    {
      "year": 1901,
      "value": 13.40634458
    },
    {
      "year": 1902,
      "value": 13.2232031
    },
    {
      "year": 1903,
      "value": 13.15892122
    },
    {
      "year": 1904,
      "value": 12.81359415
    },
    {
      "year": 1905,
      "value": 13.48959516
    },
    {
      "year": 1906,
      "value": 13.69749863
    },
    {
      "year": 1907,
      "value": 13.11628677
    },
    {
      "year": 1908,
      "value": 13.99062826
    },
    {
      "year": 1909,
      "value": 13.44662131
    },
    {
      "year": 1910,
      "value": 14.1382772
    },
    {
      "year": 1911,
      "value": 13.6809885
    },
    {
      "year": 1912,
      "value": 12.78423579
    },
    {
      "year": 1913,
      "value": 14.09387739
    },
    {
      "year": 1914,
      "value": 14.67701465
    },
    {
      "year": 1915,
      "value": 13.31261414
    },
    {
      "year": 1916,
      "value": 13.51536672
    },
    {
      "year": 1917,
      "value": 13.72114386
    },
    {
      "year": 1918,
      "value": 14.90200738
    },
    {
      "year": 1919,
      "value": 13.55496565
    },
    {
      "year": 1920,
      "value": 13.10597883
    },
    {
      "year": 1921,
      "value": 13.99115991
    },
    {
      "year": 1922,
      "value": 13.49916645
    },
    {
      "year": 1923,
      "value": 14.23392447
    },
    {
      "year": 1924,
      "value": 13.32925972
    },
    {
      "year": 1925,
      "value": 12.88371849
    },
    {
      "year": 1926,
      "value": 14.0268233
    },
    {
      "year": 1927,
      "value": 14.3327488
    },
    {
      "year": 1928,
      "value": 13.46681023
    },
    {
      "year": 1929,
      "value": 13.06101074
    },
    {
      "year": 1930,
      "value": 13.54369808
    },
    {
      "year": 1931,
      "value": 13.07829312
    },
    {
      "year": 1932,
      "value": 14.53862891
    },
    {
      "year": 1933,
      "value": 12.18614307
    },
    {
      "year": 1934,
      "value": 14.12510138
    },
    {
      "year": 1935,
      "value": 14.26780268
    },
    {
      "year": 1936,
      "value": 14.62908362
    },
    {
      "year": 1937,
      "value": 14.15648697
    },
    {
      "year": 1938,
      "value": 15.10334329
    },
    {
      "year": 1939,
      "value": 14.23937738
    },
    {
      "year": 1940,
      "value": 14.85830893
    },
    {
      "year": 1941,
      "value": 13.77398451
    },
    {
      "year": 1942,
      "value": 15.17501425
    },
    {
      "year": 1943,
      "value": 14.40498944
    },
    {
      "year": 1944,
      "value": 13.97641698
    },
    {
      "year": 1945,
      "value": 14.67611898
    },
    {
      "year": 1946,
      "value": 13.55701969
    },
    {
      "year": 1947,
      "value": 14.69686295
    },
    {
      "year": 1948,
      "value": 15.42161022
    },
    {
      "year": 1949,
      "value": 13.46249569
    },
    {
      "year": 1950,
      "value": 14.73718156
    },
    {
      "year": 1951,
      "value": 14.38255452
    },
    {
      "year": 1952,
      "value": 14.23994976
    },
    {
      "year": 1953,
      "value": 15.85058809
    },
    {
      "year": 1954,
      "value": 15.44005121
    },
    {
      "year": 1955,
      "value": 15.47547791
    },
    {
      "year": 1956,
      "value": 16.31615096
    },
    {
      "year": 1957,
      "value": 17.15195529
    },
    {
      "year": 1958,
      "value": 15.29021105
    },
    {
      "year": 1959,
      "value": 15.22729196
    },
    {
      "year": 1960,
      "value": 14.26507063
    },
    {
      "year": 1961,
      "value": 14.23152625
    },
    {
      "year": 1962,
      "value": 15.55272672
    },
    {
      "year": 1963,
      "value": 16.54757151
    },
    {
      "year": 1964,
      "value": 14.50986302
    },
    {
      "year": 1965,
      "value": 14.99270834
    },
    {
      "year": 1966,
      "value": 14.30857481
    },
    {
      "year": 1967,
      "value": 16.71314977
    },
    {
      "year": 1968,
      "value": 15.23917803
    },
    {
      "year": 1969,
      "value": 15.65229072
    },
    {
      "year": 1970,
      "value": 14.94720354
    },
    {
      "year": 1971,
      "value": 15.6740124
    },
    {
      "year": 1972,
      "value": 16.12567247
    },
    {
      "year": 1973,
      "value": 16.1786497
    },
    {
      "year": 1974,
      "value": 17.51541766
    },
    {
      "year": 1975,
      "value": 15.54676828
    },
    {
      "year": 1976,
      "value": 16.11284942
    },
    {
      "year": 1977,
      "value": 17.69201356
    },
    {
      "year": 1978,
      "value": 16.87905145
    },
    {
      "year": 1979,
      "value": 16.11221571
    },
    {
      "year": 1980,
      "value": 17.44447998
    },
    {
      "year": 1981,
      "value": 16.31993829
    },
    {
      "year": 1982,
      "value": 17.4805207
    },
    {
      "year": 1983,
      "value": 15.28180177
    },
    {
      "year": 1984,
      "value": 15.84960379
    },
    {
      "year": 1985,
      "value": 15.80076683
    },
    {
      "year": 1986,
      "value": 18.01176314
    },
    {
      "year": 1987,
      "value": 15.62800524
    },
    {
      "year": 1988,
      "value": 16.98977473
    },
    {
      "year": 1989,
      "value": 16.73580108
    },
    {
      "year": 1990,
      "value": 17.63169311
    },
    {
      "year": 1991,
      "value": 17.73377156
    },
    {
      "year": 1992,
      "value": 17.15069727
    },
    {
      "year": 1993,
      "value": 17.61820652
    },
    {
      "year": 1994,
      "value": 16.91936654
    },
    {
      "year": 1995,
      "value": 16.84479001
    },
    {
      "year": 1996,
      "value": 16.80978378
    },
    {
      "year": 1997,
      "value": 15.32016443
    },
    {
      "year": 1998,
      "value": 17.64305285
    },
    {
      "year": 1999,
      "value": 16.07369081
    },
    {
      "year": 2000,
      "value": 16.42349485
    },
    {
      "year": 2001,
      "value": 22.36666679
    },
    {
      "year": 2002,
      "value": 20.65833473
    },
    {
      "year": 2003,
      "value": 19.69999886
    },
    {
      "year": 2004,
      "value": 19.27499962
    },
    {
      "year": 2005,
      "value": 19.29166603
    },
    {
      "year": 2006,
      "value": 18.60000038
    },
    {
      "year": 2007,
      "value": 21.47500038
    },
    {
      "year": 2008,
      "value": 20.42499733
    },
    {
      "year": 2009,
      "value": 18.95833397
    },
    {
      "year": 2010,
      "value": 19.71666908
    },
    {
      "year": 2011,
      "value": 18.40833282
    },
    {
      "year": 2012,
      "value": 18.14166832
    },
    {
      "year": 2013,
      "value": 17.74166679
    },
    {
      "year": 2014,
      "value": 16.62500191
    },
    {
      "year": 2015,
      "value": 16.91666603
    },
    {
      "year": 2016,
      "value": 15.35000134
    },
    {
      "year": 2017,
      "value": 15.50833416
    },
    {
      "year": 2018,
      "value": 18.03333282
    },
    {
      "year": 2019,
      "value": 19.07499886
    },
    {
      "year": 2020,
      "value": 16.19999886
    },
    {
      "year": 2021,
      "value": 15.07499981
    },
    {
      "year": 2022,
      "value": 19.44999886
    }
  ]
}