{
  "city": "Paris",
  "country": "France",
  "data": [
    {
      "year": 1850,
      "value": 16.66075567
    },
    {
      "year": 1851,
      "value": 17.02955811
    },
    {
      "year": 1852,
      "value": 16.79308398
    },
    {
      "year": 1853,
      "value": 17.15225781
    },
    {
      "year": 1854,
      "value": 18.91360991
    },
    {
      "year": 1855,
      "value": 19.04901688
    },
    {
      "year": 1856,
      "value": 18.852042
    },
    {
      "year": 1857,
      "value": 20.41327163
    },
    {
      "year": 1858,
      "value": 18.50561953
    },
    {
      "year": 1859,
      "value": 18.55161688
    },
    {
      "year": 1860,
      "value": 19.57387742
    },
    {
      "year": 1861,
      "value": 21.42091264
    },
    {
      "year": 1862,
      "value": 20.20600606
    },
    {
      "year": 1863,
      "value": 20.52125778
    },
    {
      "year": 1864,
      "value": 22.05459769
    },
    {
      "year": 1865,
      "value": 21.05130155
    },
    {
      "year": 1866,
      "value": 21.18705844
    },
    {
      "year": 1867,
      "value": 21.28358848
    },
    {
      "year": 1868,
      "value": 21.50605898
    },
    {
      "year": 1869,
      "value": 21.51509148
    },
    {
      "year": 1870,
      "value": 21.3817769
    },
    {
      "year": 1871,
      "value": 21.75966803
    },
    {
      "year": 1872,
      "value": 21.42438947
    },
    {
      "year": 1873,
      "value": 21.59720324
    },
    {
      "year": 1874,
      "value": 22.96075035
    },
    {
      "year": 1875,
      "value": 22.47126443
    },
    {
      "year": 1876,
      "value": 22.65830478
    },
    {
      "year": 1877,
      "value": 24.45026881
    },
    {
      "year": 1878,
      "value": 21.84212616
    },
    {
      "year": 1879,
      "value": 22.47054344
    },
    {
      "year": 1880,
      "value": 23.99877183
    },
    {
      "year": 1881,
      "value": 24.59989347
    },
    {
      "year": 1882,
      "value": 25.53941348
    },
    {
      "year": 1883,
      "value": 24.26926084
    },
    {
      "year": 1884,
      "value": 24.31306033
    },
    {
      "year": 1885,
      "value": 25.9198556
    },
    {
      "year": 1886,
      "value": 24.70114941
    },
    {
      "year": 1887,
      "value": 22.80174494
    },
    {
      "year": 1888,
      "value": 23.63591436
    },
    {
      "year": 1889,
      "value": 25.85398512
    },
    {
      "year": 1890,
      "value": 26.29327951
    },
    {
      "year": 1891,
      "value": 26.19932241
    },
    {
      "year": 1892,
      "value": 26.11682905
    },
    {
      "year": 1893,
      "value": 24.81099905
    },
    {
      "year": 1894,
      "value": 26.50898791
    },
    {
      "year": 1895,
      "value": 27.04036405
    },
    {
      "year": 1896,
      "value": 25.74154876
    },
    {
      "year": 1897,
      "value": 28.00177496
    },
    {
      "year": 1898,
      "value": 29.27975957
    },
    {
      "year": 1899,
      "value": 27.58926458
    },
    {
      "year": 1900,
      "value": 29.07996592
    },
    {
      "year": 1901,
      "value": 28.1186916
    },
    {
      "year": 1902,
      "value": 28.62568093
    },
    {
      "year": 1903,
      "value": 28.21457185
    },
    {
      "year": 1904,
      "value": 29.9369318
    },
    {
      "year": 1905,
      "value": 30.57035004
    },
    {
      "year": 1906,
      "value": 29.93763967
    },
    {
      "year": 1907,
      "value": 31.90717059
    },
    {
      "year": 1908,
      "value": 32.77955695
    },
    {
      "year": 1909,
      "value": 31.69485624
    },
    {
      "year": 1910,
      "value": 34.31189912
    },
    {
      "year": 1911,
      "value": 31.07567487
    },
    {
      "year": 1912,
      "value": 34.61558833
    },
    {
      "year": 1913,
      "value": 33.12714336
    },
    {
      "year": 1914,
      "value": 29.59127732
    },
    {
      "year": 1915,
      "value": 27.67581225
    },
    {
      "year": 1916,
      "value": 28.80946808
    },
    {
      "year": 1917,
      "value": 28.52981366
    },
    {
      "year": 1918,
      "value": 26.50707828
    },
    {
      "year": 1919,
      "value": 27.85204372
    },
    {
      "year": 1920,
      "value": 29.11096137
    },
    {
      "year": 1921,
      "value": 27.59504135
    },
    {
      "year": 1922,
      "value": 30.92743373
    },
    {
      "year": 1923,
      "value": 30.08090548
    },
    {
      "year": 1924,
      "value": 33.8588932
    },
    {
      "year": 1925,
      "value": 31.90554837
    },
    {
      "year": 1926,
      "value": 31.00318526
    },
    {
      "year": 1927,
      "value": 32.94088968
    },
    {
      "year": 1928,
      "value": 33.21529487
    },
    {
      "year": 1929,
      "value": 35.63866891
    },
    {
      "year": 1930,
      "value": 36.14447708
    },
    {
      "year": 1931,
      "value": 34.04305868
    },
    {
      "year": 1932,
      "value": 29.80914761
    },
    {
      "year": 1933,
      "value": 29.97853721
    },
    {
      "year": 1934,
      "value": 33.29989445
    },
    {
      "year": 1935,
      "value": 33.15110824
    },
    {
      "year": 1936,
      "value": 32.09580355
    },
    {
      "year": 1937,
      "value": 33.96911695
    },
    {
      "year": 1938,
      "value": 34.99684875
    },
    {
      "year": 1939,
      "value": 35.04085371
    },
    {
      "year": 1940,
      "value": 31.38160949
    },
    {
      "year": 1941,
      "value": 28.00516047
    },
    {
      "year": 1942,
      "value": 27.5951934
    },
    {
      "year": 1943,
      "value": 28.55863173
    },
    {
      "year": 1944,
      "value": 25.00540359
    },
    {
      "year": 1945,
      "value": 22.64666456
    },
    {
      "year": 1946,
      "value": 27.5519593
    },
    {
      "year": 1947,
      "value": 29.54926528
    },
    {
      "year": 1948,
      "value": 29.85823426
    },
    {
      "year": 1949,
      "value": 32.2790367
    },
    {
      "year": 1950,
      "value": 31.18335922
    },
    {
      "year": 1951,
      "value": 33.41509363
    },
    {
      "year": 1952,
      "value": 32.65944469
    },
    {
      "year": 1953,
      "value": 29.39079322
    },
    {
      "year": 1954,
      "value": 33.02593352
    },
    {
      "year": 1955,
      "value": 32.70848853
    },
    {
      "year": 1956,
      "value": 32.39248346
    },
    {
      "year": 1957,
      "value": 35.97493022
    },
    {
      "year": 1958,
      "value": 31.25017796
    },
    {
      "year": 1959,
      "value": 31.03352243
    },
    {
      "year": 1960,
      "value": 34.21844703
    },
    {
      "year": 1961,
      "value": 36.53130607
    },
    {
      "year": 1962,
      "value": 38.1734911
    },
    {
      "year": 1963,
      "value": 36.95088314
    },
    {
      "year": 1964,
      "value": 36.47548921
    },
    {
      "year": 1965,
      "value": 39.04114393
    },
    {
      "year": 1966,
      "value": 34.42360077
    },
    {
      "year": 1967,
      "value": 35.22739535
    },
    {
      "year": 1968,
      "value": 35.80956925
    },
    {
      "year": 1969,
      "value": 35.48420081
    },
    {
      "year": 1970,
      "value": 34.24055637
    },
    {
      "year": 1971,
      "value": 32.75112205
    },
    {
      "year": 1972,
      "value": 33.35423842
    },
    {
      "year": 1973,
      "value": 30.77863043
    },
    {
      "year": 1974,
      "value": 35.15230958
    },
    {
      "year": 1975,
      "value": 28.76613828
    },
    {
      "year": 1976,
      "value": 28.91605116
    },
    {
      "year": 1977,
      "value": 31.72548026
    },
    {
      "year": 1978,
      "value": 32.36369018
    },
    {
      "year": 1979,
      "value": 31.4634494
    },
    {
      "year": 1980,
      "value": 31.49966474
    },
    {
      "year": 1981,
      "value": 29.66287324
    },
    {
      "year": 1982,
      "value": 26.93680213
    },
    {
      "year": 1983,
      "value": 28.04288963
    },
    {
      "year": 1984,
      "value": 25.24550357
    },
    {
      "year": 1985,
      "value": 27.31163248
    },
    {
      "year": 1986,
      "value": 25.13448003
    },
    {
      "year": 1987,
      "value": 26.20789231
    },
    {
      "year": 1988,
      "value": 24.70583062
    },
    {
      "year": 1989,
      "value": 25.12108907
    },
    {
      "year": 1990,
      "value": 24.87018806
    },
    {
      "year": 1991,
      "value": 23.9269852
    },
    {
      "year": 1992,
      "value": 23.85284614
    },
    {
      "year": 1993,
      "value": 22.40533368
    },
    {
      "year": 1994,
      "value": 21.02233928
    },
    {
      "year": 1995,
      "value": 19.78927452
    },
    {
      "year": 1996,
      "value": 19.74334185
    },
    {
      "year": 1997,
      "value": 19.53346173
    },
    {
      "year": 1998,
      "value": 17.93830354
    },
    {
      "year": 1999,
      "value": 16.35237667
    },
    {
      "year": 2000,
      "value": 16.43687123
    },
    {
      "year": 2001,
      "value": 15.91666508
    },
    {
      "year": 2002,
      "value": 16.21666908
    },
    {
      "year": 2003,
      "value": 18.07499886
    },
    {
      "year": 2004,
      "value": 15.22499943
    },
    {
      "year": 2005,
      "value": 15.98333263
    },
    {
      "year": 2006,
      "value": 16.22500038
    },
    {
      "year": 2007,
      "value": 17.14999962
    },
    {
      "year": 2008,
      "value": 17.76666832
    },
    {
      "year": 2009,
      "value": 19.25833321
    },
    {
      "year": 2010,
      "value": 21.03333282
    },
    {
      "year": 2011,
      "value": 19.65833092
    },
    {
      "year": 2012,
      "value": 18.61666679
    },
    {
      "year": 2013,
      "value": 20.51666641
    },
    {
      "year": 2014,
      "value": 15.94166565
    },
    {
      "year": 2015,
      "value": 16.85000038
    },
    {
      "year": 2016,
      "value": 15.66666698
    },
    {
      "year": 2017,
      "value": 14.95000076
    },
    {
      "year": 2018,
      "value": 15.75833416
    },
    {
      "year": 2019,
      "value": 13.88333416
    },
    {
      "year": 2020,
      "value": 12.36666775
    },
    {
      "year": 2021,
      "value": 14.15833378
    },
    {
      "year": 2022,
      "value": 13.67500019
    }
  ]
}