[
  {
    "city": "Abuja",
    "country": "Nigeria",
    "lat": 9.0667,
    "lng": 7.4833
  },
  {
    "city": "Accra",
    "country": "Ghana",
    "lat": 5.5461,
    "lng": -0.2067
  },
  {
    "city": "Addis Ababa",
    "country": "Ethiopia",
    "lat": 9.03,
    "lng": 38.74
  },
  {
    "city": "Algiers",
    "country": "Algeria",
    "lat": 36.7325,
    "lng": 3.0872
  },
  {
    "city": "Antananarivo",
    "country": "Madagascar",
    "lat": -18.91,
    "lng": 47.525
  },
  {
    "city": "Asmara",
    "country": "Eritrea",
    "lat": 15.3358,
    "lng": 38.9411
  },
  {
    "city": "Bamako",
    "country": "Mali",
    "lat": 12.6458,
    "lng": -7.9922
  },
  {
    "city": "Bissau",
    "country": "Guinea-Bissau",
    "lat": 11.85,
    "lng": -15.5667
  },
  {
    "city": "Bujumbura",
    "country": "Burundi",
    "lat": -3.3833,
    "lng": 29.3667
  },
  {
    "city": "Cairo",
    "country": "Egypt",
    "lat": 30.0444,
    "lng": 31.2358
  },
  {
    "city": "Cape Town",
    "country": "South Africa",
    "lat": -33.9253,
    "lng": 18.4239
  },
  {
    "city": "Conakry",
    "country": "Guinea",
    "lat": 9.5092,
    "lng": -13.7122
  },
  {
    "city": "Cotonou",
    "country": "Benin",
    "lat": 6.3667,
    "lng": 2.4333
  },
  {
    "city": "Dakar",
    "country": "Senegal",
    "lat": 14.6726,
    "lng": -17.432
  },
  {
    "city": "Dar es Salaam",
    "country": "Tanzania",
    "lat": -6.8161,
    "lng": 39.2803
  },
  {
    "city": "Djibouti",
    "country": "Djibouti",
    "lat": 11.5944,
    "lng": 43.1481
  },
  {
    "city": "Freetown",
    "country": "Sierra Leone",
    "lat": 8.4833,
    "lng": -13.2331
  },
  {
    "city": "Gaborone",
    "country": "Botswana",
    "lat": -24.6569,
    "lng": 25.9086
  },
  {
    "city": "Harare",
    "country": "Zimbabwe",
    "lat": -17.8292,
    "lng": 31.0522
  },
  {
    "city": "Juba",
    "country": "South Sudan",
    "lat": 4.83,
    "lng": 31.58
  },
  {
    "city": "Kampala",
    "country": "Uganda",
    "lat": 0.3136,
    "lng": 32.5811
  },
  {
    "city": "Khartoum",
    "country": "Sudan",
    "lat": 15.6031,
    "lng": 32.5265
  },
  {
    "city": "Kigali",
    "country": "Rwanda",
    "lat": -1.9536,
    "lng": 30.0606
  },
  {
    "city": "Lagos",
    "country": "Nigeria",
    "lat": 6.455,
    "lng": 3.3841
  },
  {
    "city": "Libreville",
    "country": "Gabon",
    "lat": 0.3901,
    "lng": 9.4544
  },
  {
    "city": "Lilongwe",
    "country": "Malawi",
    "lat": -13.9669,
    "lng": 33.7873
  },
  {
    "city": "Lomé",
    "country": "Togo",
    "lat": 6.1308,
    "lng": 1.2153
  },
  {
    "city": "Luanda",
    "country": "Angola",
    "lat": -8.8383,
    "lng": 13.2344
  },
  {
    "city": "Lusaka",
    "country": "Zambia",
    "lat": -15.4167,
    "lng": 28.2833
  },
  {
    "city": "Malabo",
    "country": "Equatorial Guinea",
    "lat": 3.7456,
    "lng": 8.7744
  },
  {
    "city": "Maputo",
    "country": "Mozambique",
    "lat": -25.9153,
    "lng": 32.5764
  },
  {
    "city": "Mogadishu",
    "country": "Somalia",
    "lat": 2.0392,
    "lng": 45.3419
  },
  {
    "city": "Monrovia",
    "country": "Liberia",
    "lat": 6.3133,
    "lng": -10.8014
  },
  {
    "city": "Nairobi",
    "country": "Kenya",
    "lat": -1.2864,
    "lng": 36.8172
  },
  {
    "city": "Niamey",
    "country": "Niger",
    "lat": 13.515,
    "lng": 2.1175
  },
  {
    "city": "Nouakchott",
    "country": "Mauritania",
    "lat": 18.0858,
    "lng": -15.9785
  },
  {
    "city": "Ouagadougou",
    "country": "Burkina Faso",
    "lat": 12.3686,
    "lng": -1.5275
  },
  {
    "city": "Port Louis",
    "country": "Mauritius",
    "lat": -20.1644,
    "lng": 57.5042
  },
  {
    "city": "Pretoria",
    "country": "South Africa",
    "lat": -25.7461,
    "lng": 28.1881
  },
  {
    "city": "Rabat",
    "country": "Morocco",
    "lat": 34.0209,
    "lng": -6.8416
  },
  {
    "city": "Tripoli",
    "country": "Libya",
    "lat": 32.8872,
    "lng": 13.1914
  },
  {
    "city": "Tunis",
    "country": "Tunisia",
    "lat": 36.8064,
    "lng": 10.1817
  },
  {
    "city": "Victoria",
    "country": "Seychelles",
    "lat": -4.6231,
    "lng": 55.4525
  },
  {
    "city": "Windhoek",
    "country": "Namibia",
    "lat": -22.57,
    "lng": 17.0836
  },
  {
    "city": "Yaoundé",
    "country": "Cameroon",
    "lat": 3.8667,
    "lng": 11.5167
  },
  {
    "city": "Ahmedabad",
    "country": "India",
    "lat": 23.0225,
    "lng": 72.5714
  },
  {
    "city": "Amman",
    "country": "Jordan",
    "lat": 31.9497,
    "lng": 35.9328
  },
  {
    "city": "Ankara",
    "country": "Turkey",
    "lat": 39.93,
    "lng": 32.85
  },
  {
    "city": "Ashgabat",
    "country": "Turkmenistan",
    "lat": 37.9375,
    "lng": 58.38
  },
  {
    "city": "Astana",
    "country": "Kazakhstan",
    "lat": 51.1472,
    "lng": 71.4222
  },
  {
    "city": "Baghdad",
    "country": "Iraq",
    "lat": 33.3153,
    "lng": 44.3661
  },
  {
    "city": "Baku",
    "country": "Azerbaijan",
    "lat": 40.3667,
    "lng": 49.8352
  },
  {
    "city": "Bangkok",
    "country": "Thailand",
    "lat": 13.7525,
    "lng": 100.4942
  },
  {
    "city": "Beijing",
    "country": "China",
    "lat": 39.9067,
    "lng": 116.3975
  },
  {
    "city": "Bishkek",
    "country": "Kyrgyzstan",
    "lat": 42.8667,
    "lng": 74.5667
  },
  {
    "city": "Chennai",
    "country": "India",
    "lat": 13.0825,
    "lng": 80.275
  },
  {
    "city": "Colombo",
    "country": "Sri Lanka",
    "lat": 6.9167,
    "lng": 79.8333
  },
  {
    "city": "Damascus",
    "country": "Syria",
    "lat": 33.502,
    "lng": 36.2981
  },
  {
    "city": "Delhi",
    "country": "India",
    "lat": 28.61,
    "lng": 77.23
  },
  {
    "city": "Dhaka",
    "country": "Bangladesh",
    "lat": 23.7289,
    "lng": 90.3944
  },
  {
    "city": "Doha",
    "country": "Qatar",
    "lat": 25.2867,
    "lng": 51.5333
  },
  {
    "city": "Dushanbe",
    "country": "Tajikistan",
    "lat": 38.5367,
    "lng": 68.78
  },
  {
    "city": "Hangzhou",
    "country": "China",
    "lat": 30.267,
    "lng": 120.153
  },
  {
    "city": "Hanoi",
    "country": "Vietnam",
    "lat": 21.0,
    "lng": 105.85
  },
  {
    "city": "Islamabad",
    "country": "Pakistan",
    "lat": 33.6931,
    "lng": 73.0639
  },
  {
    "city": "Jakarta",
    "country": "Indonesia",
    "lat": -6.175,
    "lng": 106.8275
  },
  {
    "city": "Jerusalem",
    "country": "Israel",
    "lat": 31.7789,
    "lng": 35.2256
  },
  {
    "city": "Kabul",
    "country": "Afghanistan",
    "lat": 34.5253,
    "lng": 69.1783
  },
  {
    "city": "Karachi",
    "country": "Pakistan",
    "lat": 24.86,
    "lng": 67.01
  },
  {
    "city": "Kathmandu",
    "country": "Nepal",
    "lat": 27.71,
    "lng": 85.32
  },
  {
    "city": "Kuala Lumpur",
    "country": "Malaysia",
    "lat": 3.1686,
    "lng": 101.698
  },
  {
    "city": "Kuwait City",
    "country": "Kuwait",
    "lat": 29.3697,
    "lng": 47.9783
  },
  {
    "city": "Manama",
    "country": "Bahrain",
    "lat": 26.2233,
    "lng": 50.5875
  },
  {
    "city": "Manila",
    "country": "Philippines",
    "lat": 14.5958,
    "lng": 120.9772
  },
  {
    "city": "Mumbai",
    "country": "India",
    "lat": 19.0761,
    "lng": 72.8775
  },
  {
    "city": "Muscat",
    "country": "Oman",
    "lat": 23.6139,
    "lng": 58.5922
  },
  {
    "city": "Nanjing",
    "country": "China",
    "lat": 32.0608,
    "lng": 118.7789
  },
  {
    "city": "Nicosia",
    "country": "Cyprus",
    "lat": 35.1725,
    "lng": 33.365
  },
  {
    "city": "Phnom Penh",
    "country": "Cambodia",
    "lat": 11.5696,
    "lng": 104.921
  },
  {
    "city": "Riyadh",
    "country": "Saudi Arabia",
    "lat": 24.65,
    "lng": 46.71
  },
  {
    "city": "Shanghai",
    "country": "China",
    "lat": 31.2286,
    "lng": 121.4747
  },
  {
    "city": "Singapore",
    "country": "Singapore",
    "lat": 1.3,
    "lng": 103.8
  },
  {
    "city": "Taipei",
    "country": "Taiwan",
    "lat": 25.0375,
    "lng": 121.5625
  },
  {
    "city": "Tashkent",
    "country": "Uzbekistan",
    "lat": 41.3111,
    "lng": 69.2797
  },
  {
    "city": "Tbilisi",
    "country": "Georgia",
    "lat": 41.7225,
    "lng": 44.7925
  },
  {
    "city": "Tehran",
    "country": "Iran",
    "lat": 35.6889,
    "lng": 51.3897
  },
  {
    "city": "Thimphu",
    "country": "Bhutan",
    "lat": 27.4722,
    "lng": 89.6361
  },
  {
    "city": "Tokyo",
    "country": "Japan",
    "lat": 35.687,
    "lng": 139.7495
  },
  {
    "city": "Ulaanbaatar",
    "country": "Mongolia",
    "lat": 47.9214,
    "lng": 106.9055
  },
  {
    "city": "Vientiane",
    "country": "Laos",
    "lat": 17.98,
    "lng": 102.63
  },
  {
    "city": "Yerevan",
    "country": "Armenia",
    "lat": 40.1814,
    "lng": 44.5144
  },
  {
    "city": "Apia",
    "country": "Samoa",
    "lat": -13.8333,
    "lng": -171.75
  },
  {
    "city": "Canberra",
    "country": "Australia",
    "lat": -35.2931,
    "lng": 149.1269
  },
  {
    "city": "Christchurch",
    "country": "New Zealand",
    "lat": -43.5311,
    "lng": 172.6361
  },
  {
    "city": "Honiara",
    "country": "Solomon Islands",
    "lat": -9.4333,
    "lng": 159.95
  },
  {
    "city": "Suva",
    "country": "Fiji",
    "lat": -18.1333,
    "lng": 178.4333
  },
  {
    "city": "Sydney",
    "country": "Australia",
    "lat": -33.8667,
    "lng": 151.2
  },
  {
    "city": "Wellington",
    "country": "New Zealand",
    "lat": -41.2889,
    "lng": 174.7772
  },
  {
    "city": "Amsterdam",
    "country": "Netherlands",
    "lat": 52.3728,
    "lng": 4.8936
  },
  {
    "city": "Antwerp",
    "country": "Belgium",
    "lat": 51.2178,
    "lng": 4.4003
  },
  {
    "city": "Athens",
    "country": "Greece",
    "lat": 37.9842,
    "lng": 23.7281
  },
  {
    "city": "Barcelona",
    "country": "Spain",
    "lat": 41.3833,
    "lng": 2.1833
  },
  {
    "city": "Belfast",
    "country": "United Kingdom",
    "lat": 54.5967,
    "lng": -5.93
  },
  {
    "city": "Belgrade",
    "country": "Serbia",
    "lat": 44.8178,
    "lng": 20.4569
  },
  {
    "city": "Berlin",
    "country": "Germany",
    "lat": 52.52,
    "lng": 13.405
  },
  {
    "city": "Bern",
    "country": "Switzerland",
    "lat": 46.948,
    "lng": 7.4474
  },
  {
    "city": "Bilbao",
    "country": "Spain",
    "lat": 43.2569,
    "lng": -2.9236
  },
  {
    "city": "Birmingham",
    "country": "United Kingdom",
    "lat": 52.48,
    "lng": -1.9025
  },
  {
    "city": "Bratislava",
    "country": "Slovakia",
    "lat": 48.1447,
    "lng": 17.1128
  },
  {
    "city": "Brighton",
    "country": "United Kingdom",
    "lat": 50.8208,
    "lng": -0.1375
  },
  {
    "city": "Brussels",
    "country": "Belgium",
    "lat": 50.8467,
    "lng": 4.3525
  },
  {
    "city": "Bucharest",
    "country": "Romania",
    "lat": 44.4325,
    "lng": 26.1039
  },
  {
    "city": "Budapest",
    "country": "Hungary",
    "lat": 47.4983,
    "lng": 19.0408
  },
  {
    "city": "Chisinau",
    "country": "Moldova",
    "lat": 47.0228,
    "lng": 28.8353
  },
  {
    "city": "Copenhagen",
    "country": "Denmark",
    "lat": 55.6805,
    "lng": 12.5615
  },
  {
    "city": "Dublin",
    "country": "Ireland",
    "lat": 53.3497,
    "lng": -6.2603
  },
  {
    "city": "Edinburgh",
    "country": "United Kingdom",
    "lat": 55.95,
    "lng": -3.1833
  },
  {
    "city": "Exeter",
    "country": "United Kingdom",
    "lat": 50.7256,
    "lng": -3.5269
  },
  {
    "city": "Florence",
    "country": "Italy",
    "lat": 43.7714,
    "lng": 11.2542
  },
  {
    "city": "Genoa",
    "country": "Italy",
    "lat": 44.4072,
    "lng": 8.934
  },
  {
    "city": "Glasgow",
    "country": "United Kingdom",
    "lat": 55.8611,
    "lng": -4.25
  },
  {
    "city": "Helsinki",
    "country": "Finland",
    "lat": 60.1708,
    "lng": 24.9375
  },
  {
    "city": "Kyiv",
    "country": "Ukraine",
    "lat": 50.45,
    "lng": 30.5233
  },
  {
    "city": "Leeds",
    "country": "United Kingdom",
    "lat": 53.7975,
    "lng": -1.5436
  },
  {
    "city": "Lisbon",
    "country": "Portugal",
    "lat": 38.7122,
    "lng": -9.134
  },
  {
    "city": "Ljubljana",
    "country": "Slovenia",
    "lat": 46.0514,
    "lng": 14.5061
  },
  {
    "city": "London",
    "country": "United Kingdom",
    "lat": 51.5072,
    "lng": -0.1275
  },
  {
    "city": "Luxembourg",
    "country": "Luxembourg",
    "lat": 49.6117,
    "lng": 6.1319
  },
  {
    "city": "Lyon",
    "country": "France",
    "lat": 45.76,
    "lng": 4.84
  },
  {
    "city": "Madrid",
    "country": "Spain",
    "lat": 40.4169,
    "lng": -3.7033
  },
  {
    "city": "Manchester",
    "country": "United Kingdom",
    "lat": 53.479,
    "lng": -2.2452
  },
  {
    "city": "Marseille",
    "country": "France",
    "lat": 43.2964,
    "lng": 5.37
  },
  {
    "city": "Milan",
    "country": "Italy",
    "lat": 45.4669,
    "lng": 9.19
  },
  {
    "city": "Minsk",
    "country": "Belarus",
    "lat": 53.9006,
    "lng": 27.5586
  },
  {
    "city": "Moscow",
    "country": "Russia",
    "lat": 55.7506,
    "lng": 37.6175
  },
  {
    "city": "Naples",
    "country": "Italy",
    "lat": 40.8358,
    "lng": 14.2486
  },
  {
    "city": "Nice",
    "country": "France",
    "lat": 43.7034,
    "lng": 7.2663
  },
  {
    "city": "Oslo",
    "country": "Norway",
    "lat": 59.9133,
    "lng": 10.7389
  },
  {
    "city": "Palermo",
    "country": "Italy",
    "lat": 38.1157,
    "lng": 13.3613
  },
  {
    "city": "Paris",
    "country": "France",
    "lat": 48.8567,
    "lng": 2.3522
  },
  {
    "city": "Prague",
    "country": "Czechia",
    "lat": 50.0875,
    "lng": 14.4214
  },
  {
    "city": "Podgorica",
    "country": "Montenegro",
    "lat": 42.4414,
    "lng": 19.2628
  },
  {
    "city": "Reykjavík",
    "country": "Iceland",
    "lat": 64.1458,
    "lng": -21.9425
  },
  {
    "city": "Riga",
    "country": "Latvia",
    "lat": 56.9475,
    "lng": 24.1069
  },
  {
    "city": "Rome",
    "country": "Italy",
    "lat": 41.8931,
    "lng": 12.4828
  },
  {
    "city": "Sarajevo",
    "country": "Bosnia and Herzegovina",
    "lat": 43.8564,
    "lng": 18.4131
  },
  {
    "city": "San Marino",
    "country": "San Marino",
    "lat": 43.9346,
    "lng": 12.4473
  },
  {
    "city": "Skopje",
    "country": "North Macedonia",
    "lat": 41.9961,
    "lng": 21.4317
  },
  {
    "city": "Sofia",
    "country": "Bulgaria",
    "lat": 42.6979,
    "lng": 23.3217
  },
  {
    "city": "Stockholm",
    "country": "Sweden",
    "lat": 59.3275,
    "lng": 18.0547
  },
  {
    "city": "Tirana",
    "country": "Albania",
    "lat": 41.3272,
    "lng": 19.8186
  },
  {
    "city": "Turin",
    "country": "Italy",
    "lat": 45.0792,
    "lng": 7.6761
  },
  {
    "city": "Valencia",
    "country": "Spain",
    "lat": 39.47,
    "lng": -0.3764
  },
  {
    "city": "Valletta",
    "country": "Malta",
    "lat": 35.8983,
    "lng": 14.5125
  },
  {
    "city": "Vatican City",
    "country": "Vatican City",
    "lat": 41.904,
    "lng": 12.453
  },
  {
    "city": "Verona",
    "country": "Italy",
    "lat": 45.4386,
    "lng": 10.9928
  },
  {
    "city": "Vienna",
    "country": "Austria",
    "lat": 48.2083,
    "lng": 16.3725
  },
  {
    "city": "Vilnius",
    "country": "Lithuania",
    "lat": 54.6872,
    "lng": 25.28
  },
  {
    "city": "Warsaw",
    "country": "Poland",
    "lat": 52.23,
    "lng": 21.0111
  },
  {
    "city": "Yakutsk",
    "country": "Russia",
    "lat": 62.03,
    "lng": 129.73
  },
  {
    "city": "Zagreb",
    "country": "Croatia",
    "lat": 45.8131,
    "lng": 15.9772
  },
  {
    "city": "Edmonton",
    "country": "Canada",
    "lat": 53.5344,
    "lng": -113.4903
  },
  {
    "city": "Guatemala City",
    "country": "Guatemala",
    "lat": 14.6417,
    "lng": -90.5133
  },
  {
    "city": "Havana",
    "country": "Cuba",
    "lat": 23.1367,
    "lng": -82.3589
  },
  {
    "city": "Managua",
    "country": "Nicaragua",
    "lat": 12.1364,
    "lng": -86.2514
  },
  {
    "city": "Mexico City",
    "country": "Mexico",
    "lat": 19.4333,
    "lng": -99.1333
  },
  {
    "city": "Ottawa",
    "country": "Canada",
    "lat": 45.4247,
    "lng": -75.695
  },
  {
    "city": "Panama City",
    "country": "Panama",
    "lat": 8.9711,
    "lng": -79.5347
  },
  {
    "city": "Port-au-Prince",
    "country": "Haiti",
    "lat": 18.5425,
    "lng": -72.3386
  },
  {
    "city": "San José",
    "country": "Costa Rica",
    "lat": 9.9325,
    "lng": -84.08
  },
  {
    "city": "San Salvador",
    "country": "El Salvador",
    "lat": 13.6989,
    "lng": -89.1914
  },
  {
    "city": "Tegucigalpa",
    "country": "Honduras",
    "lat": 14.1057,
    "lng": -87.204
  },
  {
    "city": "Toronto",
    "country": "Canada",
    "lat": 43.7417,
    "lng": -79.3733
  },
  {
    "city": "Asunción",
    "country": "Paraguay",
    "lat": -25.2945,
    "lng": -57.6435
  },
  {
    "city": "Bogotá",
    "country": "Colombia",
    "lat": 4.7111,
    "lng": -74.0722
  },
  {
    "city": "Brasília",
    "country": "Brazil",
    "lat": -15.7939,
    "lng": -47.8828
  },
  {
    "city": "Buenos Aires",
    "country": "Argentina",
    "lat": -34.6036,
    "lng": -58.3814
  },
  {
    "city": "Caracas",
    "country": "Venezuela",
    "lat": 10.4806,
    "lng": -66.9036
  },
  {
    "city": "Coyhaique",
    "country": "Chile",
    "lat": -45.5667,
    "lng": -72.0667
  },
  {
    "city": "La Paz",
    "country": "Bolivia",
    "lat": -16.4958,
    "lng": -68.1333
  },
  {
    "city": "Lima",
    "country": "Peru",
    "lat": -12.06,
    "lng": -77.0375
  },
  {
    "city": "Paramaribo",
    "country": "Suriname",
    "lat": 5.8522,
    "lng": -55.2039
  },
  {
    "city": "Santiago",
    "country": "Chile",
    "lat": -33.4372,
    "lng": -70.6506
  },
  {
    "city": "São Paulo",
    "country": "Brazil",
    "lat": -23.5504,
    "lng": -46.6339
  },
    {
    "city": "Abidjan",
    "country": "Côte d'Ivoire",
    "lat": 5.3364,
    "lng": -4.0267
  },
      {
    "city": "Bangui",
    "country": "CAR",
    "lat": 4.3733,
    "lng": 18.5628
  },
        {
    "city": "Brazzaville",
    "country": "Congo",
    "lat": -4.2634,
    "lng": 15.2429
  },
  {
    "city": "Kinshasa",
    "country": "DRC",
    "lat": -4.3250,
    "lng": 15.3222
  },
  {
    "city": "N'Djaména",
    "country": "Chad",
    "lat": 12.1348,
    "lng": 15.0557
  },
    {
    "city": "São Tomé",
    "country": "São Tomé and Príncipe",
    "lat": 0.3365,
    "lng": 6.7273
  },
      {
    "city": "Abu Dhabi",
    "country": "UAE",
    "lat": 24.4667,
    "lng": 54.3667
  },
  {
    "city": "Karnataka",
    "country": "India",
    "lat": 12.9716,
    "lng": 77.5946
  },
    {
    "city": "Pyongyang",
    "country": "North Korea",
    "lat": 39.0167,
    "lng": 125.7475
  },
  {
    "city": "Sana'a",
    "country": "Yemen",
    "lat": 15.3483,
    "lng": 44.2064
  },
  {
    "city": "Seoul",
    "country": "South Korea",
    "lat": 37.5667,
    "lng": 126.9833
  },
    {
    "city": "Seoul",
    "country": "South Korea",
    "lat": 37.5667,
    "lng": 126.9833
  },
      {
    "city": "Temirtau",
    "country": "Kazakhstan",
    "lat": 50.05,
    "lng": 72.95
  },
  {
    "city": "Nukuʻalofa",
    "country": "Tonga",
    "lat": -21.1333,
    "lng": -175.2
  },
    {
    "city": "Port Vila",
    "country": "Vanuatu",
    "lat": -17.7333,
    "lng": 168.3167
  },
      {
    "city": "Port Vila",
    "country": "Vanuatu",
    "lat": -17.7333,
    "lng": 168.3167
  },
  {
    "city": "Cardiff",
    "country": "United Kingdom",
    "lat": 51.4816,
    "lng": -3.1791
  },
  {
    "city": "Ghent",
    "country": "Belgium",
    "lat": 51.0543,
    "lng": 3.7174
  },
    {
    "city": "Krakow",
    "country": "Poland",
    "lat": 50.0647,
    "lng": 19.9450
  },
  {
    "city": "La Coruna",
    "country": "Spain",
    "lat": 43.3623,
    "lng": -8.4115
  },
    {
    "city": "Fairbanks",
    "country": "USA",
    "lat": 64.8378,
    "lng": -147.7164
  },
      {
    "city": "Los Angeles",
    "country": "USA",
    "lat": 34.0522,
    "lng": -118.2437
  },
        {
    "city": "New York City",
    "country": "USA",
    "lat": 40.7128,
    "lng": -74.0060
  },
  {
    "city": "Philadelphia",
    "country": "USA",
    "lat": 39.9526,
    "lng": -75.1652
  },
    {
    "city": "Pittsburgh",
    "country": "USA",
    "lat": 40.4406,
    "lng": -79.9959
  },
      {
    "city": "Seattle",
    "country": "USA",
    "lat": 47.6062,
    "lng": -122.3321
  },
        {
    "city": "Washington, D.C.",
    "country": "USA",
    "lat": 38.9072,
    "lng": -77.0369
  }
]